aws_eni_identifier/__init__.py
aws_eni_identifier/cli.py
aws_eni_identifier/description.py
aws_eni_identifier/identify.py
aws_eni_identifier-0.1.4.dist-info/LICENSE
aws_eni_identifier-0.1.4.dist-info/METADATA
aws_eni_identifier-0.1.4.dist-info/WHEEL
aws_eni_identifier-0.1.4.dist-info/entry_points.txt
aws_eni_identifier-0.1.4.dist-info/RECORD
