Metadata-Version: 2.1
Name: aws-eni-identifier
Version: 0.1.4
Summary: Identify to which AWS service network interface is associated
Home-page: https://github.com/fivexl/aws-eni-identifier
Author: Eremin
Author-email: haru.eaa@gmail.com
Requires-Python: >=3.9.0,<4.0.0
Classifier: Programming Language :: Python :: 3
Classifier: Programming Language :: Python :: 3.9
Classifier: Programming Language :: Python :: 3.10
Classifier: Programming Language :: Python :: 3.11
Requires-Dist: glom (>=23.1.1,<24.0.0)
Requires-Dist: typer[all] (>=0.7.0,<0.8.0)
Project-URL: Repository, https://github.com/fivexl/aws-eni-identifier
